Qmorse/__init__.py
Qmorse/bimorse.py
Qmorse/soundmorse.py
Qmorse/sounds/1_long.pcm
Qmorse/sounds/1_short.pcm
qmorse-1.1.19.dist-info/licenses/LICENSE
qmorse-1.1.19.dist-info/METADATA
qmorse-1.1.19.dist-info/WHEEL
qmorse-1.1.19.dist-info/top_level.txt
qmorse-1.1.19.dist-info/RECORD
